strava_client/__init__.py
strava_client/client.py
strava_client/constants.py
strava_client/py.typed
strava_client/enums/__init__.py
strava_client/enums/api.py
strava_client/enums/auth.py
strava_client/enums/base.py
strava_client/models/__init__.py
strava_client/models/api.py
strava_client/models/base.py
strava_client/models/requests.py
strava_client/models/settings.py
strava_client-1.0.6.dist-info/METADATA
strava_client-1.0.6.dist-info/WHEEL
strava_client-1.0.6.dist-info/licenses/LICENSE
strava_client-1.0.6.dist-info/RECORD
