Metadata-Version: 2.4
Name: strava-client
Version: 1.0.6
Summary: A lightweight Strava API client for Python.
Project-URL: Repository, https://github.com/GiovanniGiacometti/strava-client
Author: Giovanni Giacometti
License: MIT
License-File: LICENSE
Keywords: api,client,python,strava
Classifier: Operating System :: OS Independent
Classifier: Programming Language :: Python :: 3
Classifier: Programming Language :: Python :: 3.12
Requires-Python: <3.14,>=3.10
Requires-Dist: pydantic-settings>=2
Requires-Dist: pydantic>=2
Requires-Dist: requests>=2.32.3
